Workbook

Sheet Legend
A1: April 2026 General Conference - Complete Address Matrix (34 addresses)
A3: Scope | B3: All four sessions of the 196th Annual General Conference, April 4-5, 2026. Sheets in program order: SatAM, SatPM, SunAM, SunPM.
A4: Grey rows | B4: Profiled in an earlier pass (Bednar, Teh, Becerra) or held as a placeholder (Christofferson's 'The Character of Christ', which carries its own companion doc).
A5: Marker columns | B5: Twelve Fortress Sequence markers. 'X' means the address supplies usable material, not merely that the theme appears.
A6: Doctrine vs inference | B6: Thesis, scriptures, hymns, authorities, footnotes and empirical citations are drawn from the published text. Talk type, marker mapping, RM walls, Nazareth value and deliverable feed are INFERENCE - Nelson's judgment senior.
A7: Talk types | B7: Doctrinal exposition | Testimony-narrative | Litany-inventory | Audience-specific | Procedural-liturgical
A8: RM Walls | B8: Numbers refer to the twelve walls of the Scaffolding Audit in The Onward and Upward Climb.
A9: Practice items | B9: IDs refer to the Safety Checklist: D = daily, W = weekly, M = monthly, Q = quarterly/annual.
A10: Footnote counsel | B10: Counsel published only in the notes and never spoken. Thirteen confirmed instances. A body-text-only sweep loses the best material in the corpus.
A11: Empirical citations | B11: Academic, sociological or journalistic sources cited to characterize the present. Gilbert, Uchtdorf (Josephus), Renlund (Hawthorne), Stevenson (SITA, NPR), Cook (Quran, BYU Studies), Soares, Oaks.
A12: Key convergences | B12: Oaks BYU devotional Feb 10 2026 cited SIX times. 'Casual' named by five speakers. Word-census method used independently by six. Oaks 'Repentance and Change' (2003) quoted twice.
A13: Source | B13: All content drawn from the published addresses at churchofjesuschrist.org.
A14: Built | B14: August 13, 2026, with Nelson Harris.

Sheet SatAM
A1: Ord | B1: Speaker | C1: Office | D1: Title | E1: Run | F1: Talk Type | G1: Thesis (one line) | H1: Lived Experience | I1: Method / Technique | J1: Key Scriptures | K1: Hymns & Poems | L1: Authorities Cited | M1: Citation Posture | N1: Footnote Counsel | O1: Empirical Citations | P1: Primary Marker | Q1: 1 Vig | R1: 2 Mem | S1: 3 Dev | T1: 4 Equ | U1: 5 Tru | V1: 6 Wat | W1: 7 Coh | X1: 8 Int | Y1: 9 Lea | Z1: 10 For | AA1: 11 Frc | AB1: 12 Han | AC1: Anchors | AD1: Nazareth Value | AE1: RM Walls | AF1: Practice Items | AG1: Deliverable Feed | AH1: Notes
A2: 1 | B2: Dallin H. Oaks | C2: President of the Church | D2: Introduction | E2: 2:40 | F2: Procedural / liturgical | G2: This conference opens with a solemn assembly, held only at the first conference after a new President is called. | H2: None. | I2: None. | J2: None cited. | K2: None. | L2: None. | M2: None | N2: None. | O2: None. | P2: 12 Handoff | Y2: X | AB2: X | AC2: Transmissible Word | AD2: n/a | AE2: 9 | AF2: — | AG2: Fortress: succession record | AH2: The anti-Joash statement at institutional scale: on the morning a new President is sustained, the first assertion is that Christ is the head of the Church. Structure declared not to rest on the man.
A3: 2 | B3: D. Todd Christofferson | C3: 2nd Counselor, First Presidency | D3: Solemn Assembly | E3: 9:39 | F3: Procedural / liturgical | G3: The full text of the sustaining, conducted group by group. | H3: None (the act is the content). | I3: None. | J3: None cited. | K3: None. | L3: None. | M3: None | N3: None. | O3: None. | P3: 12 Handoff | T3: X | W3: X | Y3: X | AB3: X | AC3: Durable Promise | AD3: n/a | AE3: 9 | AF3: — | AG3: Fortress: Handoff marker / OT monarchy contrast | AH3: Dissent given a channel (contact your stake president). Young women 11-18 and Aaronic Priesthood vote as their own bodies before the whole Church votes together. Best contrast artifact vs. Judah's succession.
A4: 3 | B4: Patrick Kearon | C4: Quorum of the Twelve | D4: About His Business | E4: 11:21 | F4: Testimony-narrative | G4: A calling is not vacancy-filling; it is joining Christ's redeeming work, and it is tailor-made for the growth of the one called. | H4: Baptized mid-20s in London; welcomed by raised hands; bishop with the ruler extends assistant ward clerk; 'that is NOT me'; the ward clerk who sat beside him for hours; bishop's calibrated stretch. | I4: The retrospective calling audit - list your callings in order and ask what each was for. | J4: Luke 2:49; Matt 4:18-22; John 21:1-17; Mosiah 2:17,22-24; D&C 28:13; 38:27; 121:34-37; Eph 2:19-22; Philip 2:1-4; Rom 12:4-5; Prov 3:4-5; Isa 55:8-11 | K4: None. | L4: Hinckley 1995; Holland 2013; Eyring 2002; Uchtdorf 2008; General Handbook 30.0 | M4: Apostles + Handbook | N4: n.7 Holland on finite vessels; n.8 & n.15 Handbook 30.0 (no aspiring, no advancing); n.15 Eyring 'Rise to Your Call'. | O4: None. | P4: 9 Leadership | T4: X | W4: X | Y4: X | AA4: X | AC4: Durable Promise | AD4: Convert case; the inviter is the congregation itself (raised hands as welcome). | AE4: 9, 6, 4, 7 | AF4: W9, W10, M9 | AG4: RM Climb Wall 9; Shepherd's Companion | AH4: Candid on common consent: we may not always agree with those we sustain, 'and we might be right.' 'It isn't where we serve but how.' In the Lord's economy we always come out ahead - the answer to the RM time objection.
A5: 4 | B5: Kristin M. Yee | C5: 2nd Counselor, Relief Society GP | D5: Ministering - 'That Ye Love One Another' | E5: 8:56 | F5: Testimony-narrative | G5: Ministering is not a program or calling but a covenant-borne way of being; we are not called to it and not released from it. | H5: Her father at a low point; two ministering brothers drove him weekly to the temple in the next city FOR THREE YEARS; he became a temple worker; they are still his closest friends. The nervous young sister: 'I go.' | I5: None explicit; the modelled method is non-judgmental accompaniment over years. | J5: John 13:34; Rom 5:8; Matt 16:25; 25:35-40; Mosiah 18:8-11; 5:5-12; Moses 1:39; 3 Ne 27:21,27; 1 Ne 17:3; Isa 41:10; Alma 18:32; 2 Ne 32:5; Jacob 5:71 | K5: 'Praise to the Man' (29), via Oaks | L5: Uchtdorf 2010; Nelson 2018 x2, 2022 x2; Holland 2018; Cook 2024; Oaks 2012, 2014; Bednar 2014; Talmage | M5: Heavy - apostles + Handbook | N5: MAJOR. n.7 lists the five endowment covenants in full (obedience, sacrifice, gospel, chastity, consecration) with Talmage. n.14 'when you bless the one, you bless the whole.' n.29 Oaks on women and priesthood authority. | O5: None. | P5: 7 Cohesion | T5: X | W5: X | AA5: X | AB5: X | AC5: Durable Promise | AD5: BEST TEMPO CASE IN CORPUS: weekly, next city, three years, before any visible turn. Cost fully specified. | AE5: 7, 9, 12 | AF5: W11, Q8, Q9 | AG5: RM Climb Wall 7; Shepherd's Sweep | AH5: He atoned without assurance we would love Him in return (Rom 5:8). 'I find the Savior when I minister' - Wall 7 as self-interested, not only altruistic. Health improved DOWNSTREAM of spiritual change.
A6: 5 | B6: Clark G. Gilbert | C6: Quorum of the Twelve | D6: Come Home | E6: 13:08 | F6: Testimony-narrative | G6: Christ is Redeemer and Repairer; four named barriers keep people from coming home, and each has a documented breach repaired. | H6: FIVE: his own struggle for more children (Teichert painting); Tammy Anglesey (30 yrs away, wept in the parking lot, bishop's note); Luis Vargas ('don't measure up'); Justin & Kenna Valdez (doubt; the 8-yr-old son); John Raass (trapped in parents' traditions). | I6: Anchor on the primary questions - name what you DO believe and build from there; do not make resolving every question the entry condition. | J6: Isa 58:12; Luke 1:68; 2 Ne 2:6-7; Hel 5:12; D&C 107:23 (scripture-light by design) | K6: 'Softly and Tenderly Jesus Is Calling'; Shakespeare, Julius Caesar IV.iii.249-52 | L6: Oaks 1984, 2022, BYU Feb 2026; Nelson 2016, 2022 x3; Corbridge 2019; Runia 2023; Holland 2021; Wood 2003 | M6: Oaks-dominant (9x) | N6: n.16 Runia: don't chase, stay at the tree and beckon. n.9 Corbridge primary vs secondary questions. n.18 hastening alongside struggle. | O6: MAJOR AND UNIQUE. n.8 Dyer/Deseret News Dec 2025 on LDS retention + most who leave remain open to returning; n.11 Harvard GSE on youth lacking purpose + Burge/Pew on continued meaning-seeking. | P6: 3 Devotion / Return | Q6: X | R6: X | S6: X | V6: X | W6: X | AB6: X | AC6: Fixed Center; Durable Promise | AD6: FOUR case cards with barrier type + tempo (30 yrs / 1 mo / 6 mo / 2 mo). The Valdez case transmits UPWARD from an 8-year-old. | AE6: 3, 5, 6, 7, 12 | AF6: M10, M11 | AG6: Shepherd's Sweep (primary); Two Worlds; RM wanderer half | AH6: HIGHEST-PRIORITY ADDRESS FOR THE WANDERER COHORT. John Raass held BY inherited tradition vs Teh's parents WEEDING it - same marker, opposite vantage, same session. 'Helping others requires you to stay in your covenants.'
A7: 6 | B7: David A. Bednar | C7: Quorum of the Twelve | D7: All Who Have Endured Valiantly | E7: 12:59 | F7: Doctrinal exposition | G7: 'Endure to the end' means becoming possessed of the pure love of Christ - transformation, not grit. | H7: Thin by design: one item, a lifelong love-hate relationship with running. | I7: Phrase substitution (insert 'is possessed of the pure love of Christ'); word-threading on 'endure'; preposition-level reading of 'of'; structural halving of the 13th Article of Faith. | J7: Mosiah 3:19; Alma 5:12-14; 2 Cor 5:17; Moroni 7:45-48; D&C 93:11-23; D&C 121:29; A of F 1:13; Matt 10:22; 2 Ne 31:15; Alma 32:13 | K7: 'How Great the Wisdom and the Love' (195) | L7: NONE (one Gospel Topics entry only) | M7: Scripture only | N7: None of note. | O7: None. | P7: 1 Vigilance | Q7: X | T7: X | X7: X | AA7: X | AB7: X | AC7: Durable Promise | AD7: n/a | AE7: 1, 5, 11 | AF7: D2, D3, D5, M3, Q2 | AG7: Story of You (3 of 5 wanted scriptures); Convergence Thesis | AH7: PROFILED IN PROTOTYPE PASS. Supplies 3 of the 5 scriptures wanted for the Headwater. Spiritual gifts 'not results we earn solely through focused effort' = asymmetric-model evidence.
A8: 7 | B8: Michael John U. Teh | C8: Of the Seventy | D8: Follow the Prophet; He Knows the Way | E8: 8:09 | F8: Testimony-narrative | G8: Following prophets, seers, and revelators IS following Jesus Christ - not a parallel track. | H8: Parents' conversion in the Philippines and the decades-long weeding of contrary traditions under family pressure; the Japan cancer visit; the Hong Kong reflected sunlight. | I8: Notice, confess confusion, investigate, then interpret (the Hong Kong four-beat). | J8: Luke 18:22; Matt 6:20; Ezek 33:2-7; Mosiah 8:17 | K8: 'Follow the Prophet', Children's Songbook 111 | L8: Oaks 1987, 2003, 2015, 2024 - ALL FOUR | M8: Oaks only (4 of 4) | N8: None of note. | O8: None. | P8: 3 Devotion | R8: X | S8: X | U8: X | V8: X | X8: X | AB8: X | AC8: Transmissible Word | AD8: Tier-2 household case; rejection pressure from surrounding kin; decades-long tempo; micro work admitted unfinished. | AE8: 2, 3, 6, 9, 12 | AF8: D4, W3, M4, Q4 | AG8: Story of You; Nazareth Effect; RM Wall 3 | AH8: PROFILED IN PROTOTYPE PASS. Four-for-four Oaks citation on the morning of the solemn assembly = structural sustaining act.
A9: 8 | B9: Jorge T. Becerra | C9: Of the Seventy | D9: Tithing - Putting God First | E9: 8:31 | F9: Testimony-narrative | G9: Alma's 'awful dilemma' is double-mindedness (James 1:8); tithing is the mechanism by which 'first' gets assigned. | H9: Elder Cutler's single question; selling the car with no haggling at a precise figure; the friend's car and the twins; his mother's home-evening testimony (immigrant family, financial setbacks). | I9: Footnote-following (the whole talk comes out of the footnote at Alma 7:18); the single unanswered question held for days. | J9: Alma 5:12; Alma 7:3,18; James 1:8; Matt 6:33; Moses 5:5-9; Mal 3:10 | K9: None. | L9: Hinckley 2001; Bednar 2013 | M9: Prophets + apostle | N9: None of note. | O9: None. | P9: 3 Devotion | R9: X | S9: X | T9: X | X9: X | AB9: X | AC9: Durable Promise | AD9: Handoff observed from the RECEIVING end - he names the transmission event decades later. | AE9: 2, 3, 8, 10, 12 | AF9: D6, M1, M2, Q3 | AG9: Fortress Marker 3 (clinical definition); Art of Asking Questions | AH9: PROFILED IN PROTOTYPE PASS. Best clinical definition of Marker 3 in the corpus: wavering, indecisive, conflicted, lacking commitment to a single purpose. Wisdom Pyramid sequence intact (Adam obeyed before understanding).
A10: 9 | B10: Henry B. Eyring | C10: 1st Counselor, First Presidency | D10: Prayers for Peace | E10: 13:13 | F10: Doctrinal exposition | G10: Peace comes through continual prayer - and strength comes from prayer sustained BEFORE the crisis, not summoned during it. | H10: One, and the most personal in the conference: at the funeral of his wife of 61 years he felt peace and almost joy; the mourners must have wondered why he was smiling. | I10: Frame-and-return (opens and closes on John 14:27); the unspoken prayer as a form. | J10: John 14:27 (x2); Ps 9:9-10; Luke 11:9-10; Alma 34:26-27; Matt 6:6-8; Mosiah 24:12-15; D&C 19:38; ALMA 17:3; Alma 7:27 | K10: 'Sweet Hour of Prayer' (142), n.9 | L10: NONE | M10: Scripture only | N10: n.9 supplies the hymn, unspoken. | O10: None (but note the watchman's report on present-day prayer volume). | P10: 10 Fortification | Q10: X | R10: X | Z10: X | AA10: X | AC10: Transmissible Word | AD10: n/a | AE10: 1, 10, 11 | AF10: D11, D12, D13 | AG10: RM Climb Wall 10 (first doctrinal warrant); Fortress present-tense diagnostic | AH10: WALL 10'S FIRST REAL ARGUMENT. Sons of Mosiah: strength came from CONTINUED prayer, not crisis prayer. Also a First Presidency read on the present: prayers more numerous AND more heartfelt worldwide.

Sheet SatPM
A1: Ord | B1: Speaker | C1: Office | D1: Title | E1: Run | F1: Talk Type | G1: Thesis (one line) | H1: Lived Experience | I1: Method / Technique | J1: Key Scriptures | K1: Hymns & Poems | L1: Authorities Cited | M1: Citation Posture | N1: Footnote Counsel | O1: Empirical Citations | P1: Primary Marker | Q1: 1 Vig | R1: 2 Mem | S1: 3 Dev | T1: 4 Equ | U1: 5 Tru | V1: 6 Wat | W1: 7 Coh | X1: 8 Int | Y1: 9 Lea | Z1: 10 For | AA1: 11 Frc | AB1: 12 Han | AC1: Anchors | AD1: Nazareth Value | AE1: RM Walls | AF1: Practice Items | AG1: Deliverable Feed | AH1: Notes
A2: 1 | B2: D. Todd Christofferson | C2: 2nd Counselor, First Presidency | D2: Sustaining of General Authorities | E2: - | F2: Procedural / liturgical | G2: Sustaining of officers: seven GA Seventies to emeritus Aug 1; eight new GA Seventies; new Primary general presidency. | H2: None (the act is the content). | I2: None. | J2: None cited. | K2: None. | L2: None. | M2: None | N2: None. | O2: None. | P2: 12 Handoff | Y2: X | AB2: X | AC2: Durable Promise | AD2: n/a | AE2: 9 | AF2: - | AG2: Fortress: succession record | AH2: Rosemary K. Chibota sustained as Primary General President with Theresa A. Collins as second counselor, succeeding Susan H. Porter - who had spoken the previous day. Marker 12 performed twice in 24 hours.
A3: 2 | B3: Jared B. Larson | C3: Managing Director, Church Auditing Dept. | D3: Church Auditing Department Report, 2025 | E3: - | F3: Procedural / administrative | G3: Annual attestation that contributions are received and expended according to approved policy. | H3: None. | I3: None. | J3: None cited. | K3: None. | L3: None. | M3: None | N3: None. | O3: None. | P3: 8 Integrity | X3: X | AC3: - | AD3: n/a | AE3: 8 | AF3: - | AG3: Fortress: Marker 8 institutionalized | AH3: Marker 8 with a mechanism attached and reported publicly. Small in itself; structurally it is what a sound institution does that a failing one does not.
A4: 3 | B4: Gary E. Stevenson | C4: Quorum of the Twelve | D4: Lost Luggage, Redeemed Souls | E4: 11:16 | F4: Testimony-narrative | G4: Heavenly Father entrusts His most precious cargo to stewards; ministering and nurturing the rising generation are the handling. | H4: One: his own carry-on taken at the gate with essential material inside, and the anxious flight clutching the claim ticket. Plus the parent at the curb bidding farewell to a student, soldier, or missionary. | I4: KAIZEN - the quiet discipline of constantly seeking small improvements, generated by those doing the everyday work. Plus the Kansai case: 30 years, hundreds of millions of bags, zero lost. | J4: Alma 40:11; Moroni 6:4; D&C 20:53; 93:40; 115:6; 2 Ne 25:26; Matt 16:24; D&C 76:43 | K4: None. | L4: Uchtdorf 2023 (n.10 in full) & 2022; Nelson 2018; Oaks 2020; First Presidency letter 2018 | M4: Apostles + Handbook | N4: n.10 Uchtdorf's full passage: rich soil, heavenly water, remove weeds and anything blocking sunlight, then let God work His miracle. | O4: n.1 SITA - 33 million bags mishandled in 2024. n.2 NPR (May 2024) on Kansai Airport. | P4: 12 Handoff | T4: X | W4: X | AB4: X | AC4: Durable Promise | AD4: n/a | AE4: 7, 9, 12 | AF4: W14 | AG4: RM Climb (kaizen); Shepherd's Sweep | AH4: Best INSTITUTIONAL statement of Marker 12: transmission as a system with a measurable failure rate that can be driven to zero when handlers believe the cargo is precious. Bounded on purpose - 'unlike luggage, each of us is ultimately responsible.'
A5: 4 | B5: Eduardo F. Ortega | C5: Of the Seventy | D5: Christ - Author and Finisher of Our Faith | E5: 8:29 | F5: Testimony-narrative | G5: Faith is not inherited; true discipleship always begins with a personal decision. | H5: Two generations: his grandmother Mercedes joined the Church in Mendoza, Argentina in Aug 1957 when his father was six - her circumstances 'not perfect or ideal.' And his own: raised in an active home, but 'that was not enough - I needed to know for myself,' which came as a young missionary in Colombia. | I5: Experiment upon the word (Alma 32:27). The mountain image - the shortest path up is not the safest. | J5: Helaman 5:12; Matt 16:17; Alma 32:27; MORONI 6:4; 2 Ne 31:19-20; Moroni 10:32; Mosiah 5:2 | K5: None. | L5: Oaks BYU Feb 2026 (FIFTH citation); Rasband 2025; Preach My Gospel | M5: Oaks + apostle | N5: None of note. | O5: None. | P5: 12 Handoff | Q5: X | R5: X | S5: X | U5: X | AB5: X | AC5: Durable Promise | AD5: Addressed directly to recent converts: 'you may become to your families and descendants what she was to us.' | AE5: 1, 2, 12 | AF5: M16 | AG5: RM CLIMB - the Joash diagnosis stated plainly | AH5: 'Our family heritage is a great blessing, but it is not a substitute.' The Scaffolding Audit's central claim, preached. Also: the invitation is the same whether the gospel has been in your family for generations or you were baptized last week.
A6: 5 | B6: Wan-Liang Wu | C6: Of the Seventy | D6: 'I Will Give Away All My Sins to Know Thee' | E6: 8:25 | F6: Testimony-narrative | G6: The old king of Alma 22 asked the deciding question: what am I willing to give up to know God? | H6: Born into a non-Christian family in Taiwan; as a boy accompanied his mother to Chinese temples, petitioning the god of riches for work and the god of healing for health, and loving the cakes afterward. At ten the family moved to Bolivia; he met the missionaries, felt peace though he couldn't understand the Spanish, and told his sisters he'd already decided. | I6: The conditional seeker's prayer: 'if there is a God, and if thou art God, make thyself known unto me' (Alma 22:18). | J6: Alma 22:12-18; John 17:3; 14:6; D&C 58:28; Luke 18:22; 2 Ne 25:20 | K6: None. | L6: OAKS 'Repentance and Change' (2003) - SECOND citation this conference; Preach My Gospel | M6: Oaks only | N6: None of note. | O6: None. | P6: 3 Devotion | R6: X | S6: X | U6: X | AB6: X | AC6: Durable Promise | AD6: The invitee decided BEFORE the invitation was extended - the inviter's timing was not the operative variable. | AE6: 3, 5 | AF6: M17 | AG6: Fortress Marker 3 (syncretism, purest form); Story of You | AH6: The god of riches and the god of healing IS the blend, literally. Same Oaks 2003 passage Teh quoted - both speakers converts or children of converts from non-Christian traditions. The king's household and several cities followed one decision.
A7: 6 | B7: David J. Wunderli | C7: 1st Counselor, Young Men General Presidency | D7: Jesus Christ Is Not Our Burden; He Is Our Relief | E7: 9:17 | F7: Testimony-narrative | G7: When the pack gets heavy, the one thing you must not remove is the Savior. | H7: The conference's best teaching image: his six-year-old son packed only a picture of Christ for a family hike, then filled the pack with rocks and placed the picture back on top. One step forward, five steps backward, then the fall. When his father suggested removing the picture to lighten the load, the boy's face said 'Dad, you're not as smart as I thought you were.' Plus 16-year-old Joshua in West Africa answering 'Relief.' | I7: The four-part daily keeping practice: kneel and pray with real intent; study daily, especially the Book of Mormon; daily repentance; live covenants daily and renew weekly. | J7: Moses 6:34 (x3); John 16:33; Alma 7:11-12; 34:26; 37:6,37; Moroni 7:41; Ether 12:27; Mosiah 24:13-15; 26:30; Matt 11:28-30; D&C 20:77 | K7: None. | L7: Nelson 2017 & 2019; Kearon 2025; Oaks 1996 & 2025; Richard G. Scott 2007 | M7: Apostles | N7: MAJOR. n.14 names ADDICTION and quotes Nelson on immunization against pornography and mind-numbing addictions. n.8 Nelson on daily repentance as process not event. n.16 Kearon - 'He hasn't set a limit on your second chances... your second or third or fourth - or hundredth.' | O7: None. | P7: 10 Fortification | Q7: X | S7: X | Z7: X | AA7: X | AC7: Durable Promise | AD7: n/a | AE7: 1, 10, 11 | AF7: D17, D18, M15 | AG7: Addiction-recovery companion (core image); RM Wall 10 | AH7: Rocks collect 'some by choice and some by the very nature of your journey' - removes shame from half the load without excusing the other half. Tightest version of the Climb's Part 4 in the corpus, from the office closest to Ben's cohort.
A8: 7 | B8: Gerald Causse | C8: Quorum of the Twelve | D8: Love All; Love Each | E8: 11:27 | F8: Doctrinal exposition | G8: God's love operates on two scales at once - universal in reach, personal in application - and disciples must do both. | H8: Two: the dark countryside night where his eyes adjusted and the sky filled with stars; and the journalist's question after his ordination, answered instantly - 'I have learned that I can love even more.' | I8: THE WORD-PAIR CENSUS - dozens of verses where 'all' and 'each' (or 'every') appear together; n.9 lists eighteen. Fifth census instance, first on a pair. | J8: Ps 8:3-5; Matt 10:29-31; 5:46-47; 18:1-5; Mosiah 27:30; Moroni 6:4; Luke 15:4-7; 17:12-19; John 4:5-29; 3 Ne 17:21-24 | K8: 'His Eye Is on the Sparrow' (1905 origin recounted); Beauty and the Beast | L8: Neal A. Maxwell 2002 ('God is in the details'); Joseph Smith; Nelson 2002 | M8: Predecessors + Nelson | N8: n.9 the eighteen-reference all/each list. n.16 extending love beyond congregations. | O8: None (but Beauty and the Beast is a popular-culture citation). | P8: 7 Cohesion | T8: X | W8: X | AA8: X | AB8: X | AC8: Durable Promise | AD8: 'To love all and to love each are not two different kinds of love but the same divine love expressed on two scales.' | AE8: 4, 7, 9 | AF8: W15 | AG8: NAZARETH EFFECT (macro/micro axis, stated as doctrine) | AH8: The framework's own axis articulated by an Apostle. Also the order correction: 'we don't serve only those we already love; we come to love people as we serve them.' Belle and the Beast pairs with Oaks's nurse.
A9: 8 | B9: Brian J. Holmes | C9: Of the Seventy | D9: Jesus Christ Is the Way | E9: 8:15 | F9: Testimony-narrative | G9: Christ is not only the guide; He is the path. Bound to Him by covenant and following His prophet, we walk the one way home. | H9: The Jungfrau-Marathon in the Swiss Alps with his wife Maggie - 6,400 feet of climb, the final stretch steep and narrow, single file. And the runner who finished it BLIND, tethered to a guide who moved ahead as the course steepened, calling out every obstacle. | I9: None explicit; the tether is the argument. | J9: John 14:6; 3:5; 6:66-69; Luke 10:16; Eph 2:20; 4:14; D&C 1:16; 82:10; 124:45; 2 Ne 31:17-20; Mosiah 3:13; 1 Ne 8:26-27; 11:34-36 | K9: None. | L9: Oaks 2025, 2021, BYU Feb 2026 (SIXTH citation); Christofferson 2021; Bednar 2023 | M9: Oaks-dominant | N9: n.19 - the great and spacious building stood high in the air, i.e. IT HAD NO FOUNDATION, and the fall thereof was exceedingly great; its occupants fight against the Apostles of the Lamb. | O9: None. | P9: 6 Watchmen | Q9: X | V9: X | X9: X | Y9: X | Z9: X | AC9: Durable Promise | AD9: n/a | AE9: 1, 6, 8, 9 | AF9: - | AG9: FORTRESS + SCAFFOLDING AUDIT (three standing items) | AH9: 'COVENANT BLESSINGS FLOW FROM ONGOING FAITHFULNESS, NOT MERELY FROM PAST PARTICIPATION.' Plus the apostasy mechanism in four clauses: perception of Christ becomes whatever we want Him to be; doctrine shifts; commitment erodes; unity dissolves.
A10: 9 | B10: Clement M. Matswagothata | C10: Of the Seventy | D10: He Knows You by Name | E10: 9:29 | F10: Testimony-narrative | G10: He knows each of us by name, and the most eternity-shaping name we can receive is His. | H10: Early as a young stake president: they had just buried his mother; two weeks later he stood at another graveside with his counselor, mourning the counselor's teenage son. Driving to a ward conference he poured out his heart - and a Primary boy stopped him: 'We need to talk. When are you going to stop being a naughty boy? Every morning and every night, my parents ask us to pray for you.' | I10: The by-name catalogue - Adam in Eden, Mary at the tomb, Saul on the road, Joseph in the Grove. Sixth catalogue instance. | J10: Ex 33:17; Gen 3:9; John 20:16; 17:3; 8:12; 10:11; Acts 9:4; JS-H 1:17; Alma 7:11-13; D&C 121:1; 88:6; Isa 40:31; 3 Ne 25:2 | K10: 'A Child's Prayer', Children's Songbook 12 | L10: Christofferson 2022 - 'rather than get angry with God, get close to God' | M10: One apostle | N10: None of note. | O10: None. | P10: 7 Cohesion | R10: X | S10: X | V10: X | W10: X | AB10: X | AC10: Durable Promise | AD10: A household practice (praying by name, twice daily) becoming another person's revelation. | AE10: 2, 6, 7 | AF10: D19, W16 | AG10: Shepherd's Companion; Quotable | AH10: 'The question should never be Will the Savior walk with me? He will. The real question is Will I walk with Him?' Fourth speaker to name casualness. Echoes Ortega: we honor those who came before, but above all we honor Him.
A11: 10 | B11: Ulisses Soares | C11: Quorum of the Twelve | D11: Jesus Christ - the True Vine | E11: 11:40 | F11: Doctrinal exposition | G11: 'True' vine implies false ones; in a world of many voices, staying connected is essential to spiritual survival. | H11: One: Elder Jeffrey R. Holland calling him by phone to welcome him to the Quorum of the Twelve, minutes after the invitation - feeling the Savior minister through the voice of an anointed servant. | I11: Abiding defined operationally as a list of five constant choices, including governing words in digital spaces. | J11: John 15:1,4,5; Luke 24:28-29; Col 2:8; 2 Ne 28:21; MOSIAH 2:41; 2 Cor 5:17; 1 John 2:5-6; Ex 3:14; Matt 11:28-30; D&C 84:45 | K11: None. | L11: The Living Christ; Oaks, For the Strength of Youth Q&A (Jan 2026) | M11: Oaks + scripture | N11: None of note. | O11: 'Popular philosophies spread through various forms of media' - the fullest information-environment diagnosis of the conference. | P11: 3 Devotion / 10 Fortification | Q11: X | S11: X | U11: X | V11: X | Z11: X | AC11: Transmissible Word | AD11: The Emmaus reading: He made as though He would have gone further; without the desire and then the INVITATION, nothing would have changed. | AE11: 3, 5, 10 | AF11: D20 | AG11: RM Wall 10 (media, fully supplied); Cycle of Apostasy | AH11: CLOSES THE MEDIA GAP: tangled vines rooted in popular philosophies that 'quietly introduce doubt and division - first in the mind and then in the heart,' and may 'even appear to be connected to Christ and His gospel.' Counsel is discernment, not prohibition.

Sheet SunAM
A1: Ord | B1: Speaker | C1: Office | D1: Title | E1: Run | F1: Talk Type | G1: Thesis (one line) | H1: Lived Experience | I1: Method / Technique | J1: Key Scriptures | K1: Hymns & Poems | L1: Authorities Cited | M1: Citation Posture | N1: Footnote Counsel | O1: Empirical Citations | P1: Primary Marker | Q1: 1 Vig | R1: 2 Mem | S1: 3 Dev | T1: 4 Equ | U1: 5 Tru | V1: 6 Wat | W1: 7 Coh | X1: 8 Int | Y1: 9 Lea | Z1: 10 For | AA1: 11 Frc | AB1: 12 Han | AC1: Anchors | AD1: Nazareth Value | AE1: RM Walls | AF1: Practice Items | AG1: Deliverable Feed | AH1: Notes
A2: 1 | B2: Dieter F. Uchtdorf | C2: Acting President, Quorum of Twelve | D2: Encounter at the Empty Tomb | E2: 12:28 | F2: Doctrinal exposition | G2: The women came without expecting a miracle; each of us must encounter the empty tomb ourselves, then carry the witness outward. | H2: Almost none, deliberately: he says twice he has tried to imagine their grief and can't. One line - he has stood at the tomb. | I2: The present-tense test; come-and-see then go-and-tell (in order); the inventory question - what HAVE you seen, felt, experienced? | J2: Luke 24:1-6; Matt 28:5-7,19; Mark 16:15; John 1:5; 14:6; 20:29; Rom 8:31,35-39; 3 Ne 5:3; Mosiah 5:2; Moses 1:4 | K2: 'Upon the Cross of Calvary' (184); 'I Know That My Redeemer Lives' (136) | L2: NONE | M2: Scripture only | N2: MAJOR. n.13 catalogues the women by Gospel, cites Josephus (Antiquities 4.8.15) on women's testimony being inadmissible, notes the credibility argument, then the equity doctrine: God weighs not income, station, gender, education, reputation. | O2: n.13 Josephus, classical source. First external classical citation in the sweep. | P2: 5 Truth | R2: X | T2: X | U2: X | AB2: X | AC2: Transmissible Word | AD2: They came without expecting a miracle - devotion without resolution. | AE2: 5, 12 | AF2: D16 | AG2: Two Worlds (unlikely-witnesses argument); RM Wall 5 | AH2: Third apostle in the sweep citing no living authority. 'Some hesitate because of unresolved questions' - step forward anyway; the dawn of understanding follows. Pairs with Gilbert's anchor-on-what-you-believe.
A3: 2 | B3: Emily Belle Freeman | C3: Young Women General President | D3: Best Days and Worst Days | E3: 8:39 | F3: Testimony-narrative | G3: Mortality is a proving ground; testimony is built day after day across best days and worst, not forged in a moment. | H3: One, current: planning their daughter's wedding when the oncologist called about her husband Greg's returning cancer. n.1 updates - six rounds of radiation finished before the talk, doctors optimistic. | I3: The three-lens life reading: take one figure and read them for eternal truths, invitations, and promised blessings. Peter is the worked example. | J3: Matt 16:13-17,21-23; Matt 14:28-30; Luke 22:32-34,43,48,61; John 21:17; Moses 6:34; D&C 3:9-10 | K3: None. | L3: None. For the Strength of Youth (2025) quoted six times. | M3: Manual, not persons | N3: n.10 pairs Peter with Joseph Smith at his worst (D&C 3:9-10, 'thou art still chosen'). n.11 - Peter was a skilled fisherman, never trained as a shepherd. | O3: None. | P3: 1 Vigilance | Q3: X | R3: X | Y3: X | AA3: X | AB3: X | AC3: Durable Promise | AD3: n/a | AE3: 1, 9, 11 | AF3: - | AG3: Story of You (the narrative reframe); RM Wall 1 & 9 | AH3: 'He wasn't shouting instructions from the shore or offering advice from the safety of the boat. He was in the water.' Peter's history is true told as three failures AND told as walking on water - both true; the second is the Lord's version.
A4: 3 | B4: Pedro X. Larreal | C4: Of the Seventy | D4: I Feel My Savior's Love | E4: 7:54 | F4: Doctrinal exposition | G4: The weekly sacrament, deliberately prepared for, is how the Holy Ghost's influence is renewed and the Savior's love is felt. | H4: None. First conference address. | I4: The pronoun argument - 'my body which is given for YOU'; the Lord uses the second person deliberately and repeatedly. | J4: 3 Ne 18:11; 3 Ne 9:20; Luke 22:19-20; D&C 20:77 | K4: None in address; 'As Now We Take the Sacrament' (169) linked | L4: Oaks BYU Feb 2026 (opens the address); Oaks 2008 x2; Nelson 2018 | M4: Oaks-dominant | N4: None of note. | O4: None. | P4: 10 Fortification | R4: X | S4: X | Z4: X | AC4: Durable Promise | AD4: n/a | AE4: 2, 10 | AF4: W12 | AG4: RM Wall 10 (device discipline); Feast practice | AH4: CLOSES A STANDING GAP: first explicit media/device counsel in the sweep - not a time for secular books or magazines, nor for checking cell phones. Fourth citation of the Oaks BYU devotional.
A5: 4 | B5: Edward B. Rowe | C5: Of the Seventy | D5: Choose Jesus Christ as Your Guide | E5: 9:21 | F5: Testimony-narrative | G5: Christ is a perfect and personal guide through terrain seeded with hidden dangers, with power to heal those who misstep. | H5: One, extended: as a young lawyer resolving a border dispute, walking a former war zone with thousands of undetected land mines, following his guide Winta - who escaped the war and volunteered to stay and observe. Where he steps, you step. | I5: None explicit; the modelled discipline is following a few paces behind, attending every step. | J5: Luke 18:22; Matt 4:19; 11:28; Moses 6:34; 3 Ne 9:13-14; 18:16; 27:21; 2 Ne 26:33; Mosiah 3:8,19; Rom 3:23; Moroni 7:27-28; Isa 41:10; 43:1,3 | K5: None. | L5: Oaks 2024 (n.13); Oaks Church News interview 2025; Nelson 2024 & 2022 (hesed, n.11) | M5: Oaks + Nelson | N5: **THE SINGLE BEST RM FIND OF THE SWEEP.** n.13: he became CASUAL in following his guide, attention drifting, until news of a casualty resharpened focus - 'why did I ever allow myself to become casual when I knew that casualness could lead to casualties?' Never spoken. | O5: None. | P5: 1 Vigilance / 10 Fortification | Q5: X | V5: X | Y5: X | Z5: X | AA5: X | AC5: Transmissible Word | AD5: n/a | AE5: 1, 6, 10 | AF5: D15 | AG5: RM Climb - Scaffolding Audit diagnosis in the speaker's own words | AH5: Names the drift mechanism (casualness), its cost (casualties), and confesses it in himself - in a setting where the danger was real and invisible. Also: confidence grew by walking, not by being told.
A6: 5 | B6: Ronald A. Rasband | C6: Quorum of the Twelve | D6: He Is Risen | E6: 10:21 | F6: Doctrinal exposition | G6: The Resurrection is the core doctrine of the Church, and the risen Lord is known by His outstretched hands. | H6: One: his grandson Paxton, born with a rare chromosomal deletion, who lived three years, could not speak, crawl, walk or run - but whose hands reached out. The priesthood blessing citing John 9:3, and the family's increased trust. | I6: The hands catalogue - trace one physical image across the whole ministry (Peter sinking, Bethesda, washing feet, breaking bread, Bountiful, Isaiah 49:16). | J6: 3 Ne 11:7-15; 17:7,11,21,25; Luke 24:5-6,39; John 5:26; 9:3; 14:3,19; 20:16; Alma 11:43; Ps 30:5; Isa 41:10; 49:16; D&C 76:17 | K6: 'He Is Risen!' (199) | L6: Joseph Smith (Teachings ch.3); Oaks 'Resurrection' (2000) | M6: Predecessors | N6: n.11 - the women waited to attend the body in honor of the Sabbath (Luke 23:56). n.20 on Holy Land terminology. | O6: None. | P6: 2 Memory | R6: X | W6: X | AA6: X | AB6: X | AC6: Durable Promise | AD6: n/a | AE6: 2, 11 | AF6: - | AG6: Shepherd's Companion (disability, child loss); Fortress Part IV terminal zone | AH6: Resurrection reaches the just AND the unjust; every knee shall bow. 'Resurrected whole and perfect' is the conference's clearest promise for anyone carrying a disability or a lost child.
A7: 6 | B7: Dale G. Renlund | C7: Quorum of the Twelve | D7: Because of Jesus Christ | E7: 11:00 | F7: Doctrinal exposition | G7: Not all matters are of equal value; when concerns compete, the answer is a fixed focus on Christ, not more effort. | H7: One, and it is the session's best image: their toy poodle Lady, given two balls at once, oscillating between blue and yellow until she gave up, walked to her basket, and lay down. | I7: None explicit; argues in hymn text the way Bednar argues in scripture. | J7: Alma 34:31; 11:37,40; 31:38; Mosiah 15:7-10; 26:29-30; Matt 28:18; John 14:6; 2 Ne 2:1-2,8; Ezek 33:12,14-16; Zeph 3:17; D&C 137:9; 138:3,15-17 | K7: SEVEN hymns incl. 'Where Can I Turn for Peace?' (129, x2), 'How Firm a Foundation' (85), 'I Will Walk with Jesus' (stanza quoted) | L7: Oaks x5 (2007, 2015, 2021, 2022, 2025); Nelson x2; Joseph Smith; Ballard 1987 | M7: Oaks-dominant | N7: n.16 glosses Hawthorne's The Scarlet Letter in full. n.23 cites Ballard on suicide for the proposition that only Christ can weigh every factor. | O7: n.16 Hawthorne (1850), literary. n.35 etymology of 'keep your eye on the ball'. | P7: 4 Equity | Q7: X | T7: X | U7: X | AA7: X | AC7: Durable Promise | AD7: n/a | AE7: 1, 4, 11 | AF7: M12 | AG7: Wisdom Pyramid / prioritization; wanderer's return | AH7: 'If everyone, then anyone. If anyone, then even one. And if even one, then even you.' No spiritual scar, track, or trace; no scarlet letter. Lady's failure mode is oscillation, not laziness - the RM re-entry diagnosis.
A8: 7 | B8: Thierry K. Mutombo | C8: Of the Seventy | D8: The Joy of a Covenant Relationship with God | E8: 10:19 | F8: Testimony-narrative | G8: Covenant relationship deepens divine love and holds when inherited tradition and extended family push the other way. | H8: The hardest account in the corpus: four of their ten children died early in the marriage, the last being nine-month-old Allan, found in his crib. After the funeral the extended families decided WITHOUT CONSULTING THEM that tradition required separation. He came out with empty hands and refused. | I8: The paschal greeting as opening and closing frame ('Christ is risen' / 'Truly, He is risen'). | J8: 3 Ne 9:14,17; D&C 121:1-2; 2 Ne 2:27; Mosiah 3:19; Luke 16:15; Mark 7:8; Acts 3:16; 1 Cor 15:19,22 | K8: 'Where Can I Turn for Peace?' (129), Emma Lou Thayne named | L8: Oaks 2024 & 2013; Ezra Taft Benson (test/task/commandment); Bednar 2008 | M8: Oaks + predecessor | N8: n.12 Benson's three-part frame in full. | O8: None. | P8: 3 Devotion | S8: X | W8: X | AA8: X | AB8: X | AC8: Fixed Center; Durable Promise | AD8: The covenant unit holding AGAINST the kin group - inverting the usual pressure direction. | AE8: 3, 7, 11 | AF8: - | AG8: Fortress Marker 3 (severest case); Cross-faith (paschal greeting) | AH8: 'My prayers did not change His mind and will.' The conference's honest 'no' answer to prayer - set beside Freeman's yes and Eyring's burdens-made-light. Marker 3's third vantage: Teh weeded tradition, Raass was held by it, Mutombo refused it publicly.
A9: 8 | B9: Alan R. Walker | C9: Of the Seventy | D9: A Peculiar Treasure | E9: 8:24 | F9: Litany / inventory | G9: Exodus 19:5 sets two conditions for becoming the Lord's treasure - obey His voice and keep His covenant - and it is neither casual nor accidental. | H9: One: as a boy at his grandparents' home at the base of the Andes in Mendoza, Argentina, breaking open shiny rocks hoping for something precious - only ever finding more glittering minerals. | I9: The word census on 'treasure' - dozens of warnings, then the one passage where the Lord calls US His treasure. FOURTH independent census instance. | J9: Exodus 19:5 (x2); Moses 1:39; John 3:16; 15:13; D&C 97:8 | K9: None. | L9: Nelson 2022 (3rd conference citation); Oaks 2024 (3rd citation); Christofferson 2009 | M9: Apostles | N9: None of note. | O9: None. | P9: 8 Integrity | Q9: X | T9: X | X9: X | AC9: Durable Promise | AD9: n/a | AE9: 4, 8 | AF9: M13, M14 | AG9: RM header (the acceptance criterion) | AH9: D&C 97:8 is the anti-Joash acceptance test: honest hearts, broken, contrite spirits, willing to observe covenants by sacrifice. 'The Lord does not ask for perfection all at once.' Third speaker this session to use 'casual'.
A10: 9 | B10: Dallin H. Oaks | C10: President of the Church | D10: Alive in Christ | E10: 13:38 | F10: Testimony-narrative | G10: Belief in a literal, universal resurrection changes the whole perspective of mortal life - and the consequence is to love adversaries and be peacemakers. | H10: One, the best in the session: the woman in the yellow dress he felt impressed to call on at a stake conference - a nurse who despised her most repulsive patient, until she found him thrashing in broken glass and blood and felt an electric current of God's love toward him. He died saying he wanted to go home. | I10: Philological: the full meaning of 'enemies' in King James's sources extends to any who actively oppose - so today, 'love our adversaries.' | J10: Alma 11:43-44; Matt 5:9,43-44; 22:37-39; Luke 10:29-37; 1 John 4:19; 3 Ne 12:9; Mosiah 5:2 | K10: None. | L10: David O. McKay; Howard W. Hunter; Joseph Smith (Journal, JS Papers); Nelson 2023 | M10: Predecessors only | N10: None of note. | O10: 'Many current writers characterize the time in which we live as toxic' - sourced diagnosis of the present. | P10: 7 Cohesion | U10: X | W10: X | AA10: X | AB10: X | AC10: Durable Promise | AD10: The nurse is the extreme case: the transformation ran in the INVITER, not the invitee. | AE10: 4, 7, 11 | AF10: W13 | AG10: FORTRESS THESIS (individual reformation); Two Worlds | AH10: 'Only by individual reformation can an entire society eventually rise above such evils.' The Fortress Sequence's core claim from the highest source. Also the honest double bind: accused of no love when keeping commandments, accused of endorsement when showing love.

Sheet SunPM
A1: Ord | B1: Speaker | C1: Office | D1: Title | E1: Run | F1: Talk Type | G1: Thesis (one line) | H1: Lived Experience | I1: Method / Technique | J1: Key Scriptures | K1: Hymns & Poems | L1: Authorities Cited | M1: Citation Posture | N1: Footnote Counsel | O1: Empirical Citations | P1: Primary Marker | Q1: 1 Vig | R1: 2 Mem | S1: 3 Dev | T1: 4 Equ | U1: 5 Tru | V1: 6 Wat | W1: 7 Coh | X1: 8 Int | Y1: 9 Lea | Z1: 10 For | AA1: 11 Frc | AB1: 12 Han | AC1: Anchors | AD1: Nazareth Value | AE1: RM Walls | AF1: Practice Items | AG1: Deliverable Feed | AH1: Notes
A2: 1 | B2: D. Todd Christofferson | C2: 2nd Counselor, First Presidency | D2: The Character of Christ | E2: 12:11 | F2: Doctrinal exposition | G2: Peter's question - what manner of persons ought ye to be - is answered by acquiring Christ's character; and character is downstream of motive. | H2: One, and it is borrowed: Bednar's account of the mother who, on learning her own daughter had died in the crash, turned immediately to the two other mothers. 'No self-pity; no turning inward.' | I2: The motive-first inversion: don't work on attributes, work on the thoughts, desires and intents of the heart that produce them. Three motivations named, each with its attribute cluster. | J2: 2 Peter 3:3-14; Mosiah 5:2,7; Alma 5:12,14,26; HELAMAN 15:7; Moroni 7:47-48; John 4:34; 15:13; 19:26-27; Mark 10:43,45; Matt 11:29; Heb 4:15; D&C 84:20; 121:43; 82:19; Moses 1:39 | K2: None in address. | L2: Bednar, BYU-Idaho symposium 2003; Oaks BYU Feb 2026 (SEVENTH citation); Nelson 2025 (his final address as President); Kim B. Clark 2022 | M2: Apostles + predecessor | N2: MAJOR, three items. n.7 - perfection is not to be fully realized in mortality; look forward not with dread but joyful anticipation. n.14 - ENOS'S THREE-STAGE PRAYER: self, then his people, then the enemies of his people, 'with many long strugglings.' n.19 - Zion as every man seeking his neighbor's interest; Jesus is not jealous of His powers. | O2: n.28 Alexander Balmain Bruce, The Training of the Twelve (2nd ed. 1877) - the mirrors must be finely polished. | P2: 11 Force (restraint) | T2: X | U2: X | V2: X | AA2: X | AB2: X | AC2: Durable Promise | AD2: TEMPO HYPOTHESIS CONFIRMED: instantaneous for some, incremental for most, 'the outcome is the same and equally valid.' | AE2: 1, 4, 5, 6, 9, 11 | AF2: D21, M18 | AG2: FORTRESS THESIS (aggregation of individual choices); Story of You (causal order); Nazareth tempo | AH2: 'It is the aggregation of individual choices over time that forms and changes societies for good OR ILL' - the Fortress claim with its mechanism named and running both directions. Also: 'it is not simply a matter of our striving' (asymmetric model, 3rd instance). Missionaries named as the paradigm of selflessness. Repentance cadence supplied: 'keep repenting to improve.'
A3: 2 | B3: Chi Hong (Sam) Wong | C3: Of the Seventy | D3: Remember, Remember | E3: 8:00 | F3: Litany / inventory | G3: God planted His reminders in the Book of Mormon and marked them with a doubled word; five verses carry the whole plan. | H3: One, and it is a method: ten years ago, pondering three questions, a clear thought came that the reminders would be in the Book of Mormon. | I3: The repeated-phrase census (find every instance of a doubled phrase and read them as a set); recap-as-mnemonic (restate as a numbered list and re-teach it). | J3: Mosiah 2:41; Alma 37:13; Hel 5:9; Hel 5:12; Hel 14:30; Job 38:7 | K3: None. | L3: Oaks 2024 (kite and string); Bednar 2024 (anchor pins; receive/review/remember/renew) | M3: Two living apostles | N3: None of note. | O3: None. | P3: 2 Memory | R3: X | S3: X | U3: X | Z3: X | AC3: Transmissible Word; Durable Promise | AD3: n/a | AE3: 2, 10 | AF3: M5 | AG3: Fortress Marker 2; RM Wall 10 | AH3: Best guardrail image in the corpus: the string is what holds the kite against mortal winds. Terminal contrast stated as a pair (Mosiah 2:41 vs Alma 37:13).
A4: 3 | B4: Aaron T. Hall | C4: Of the Seventy | D4: I Glory in My Jesus | E4: 8:29 | F4: Litany / inventory | G4: 'My Jesus' is a possessive, not a formality; glorying deepens by knowing His names and what each one does. | H4: Essentially none personal - the value is entirely in the method and reference set. | I4: The name inventory (60+ names in 1-2 Nephi; work six, then assign the hearer their own); Nephi's four-reasons-plus-one-commitment witness template (2 Ne 4:20-21,34). | J4: 2 Ne 33:6; 4:20-21,34; 31:19,21; Alma 26:16; 5:33,60; Isa 49:16; D&C 88:63; D&C 19:23; Mosiah 28:4; D&C 45:3,5 | K4: None. | L4: Kearon 2024; Renlund 2024 & 2021; Nelson 2022; Oaks 2021; The Living Christ | M4: Apostle-dense | N4: None of note. | O4: None. | P4: 3 Devotion | R4: X | S4: X | Y4: X | AA4: X | AC4: Durable Promise | AD4: Ammon named as one who walked a path of rebellion and sin - the corpus's key figure for the returned-and-fallen. | AE4: 3, 11 | AF4: D8, D9, M7 | AG4: RM wanderer half; Story of You (transform/save/exalt) | AH4: D&C 88:63 + 19:23 give a three-step daily practice: draw near, and to do so learn of Him, listen to His words, walk with Him.
A5: 4 | B5: Susan H. Porter | C5: Primary General President | D5: 'Here Am I, Send Me' | E5: 8:44 | F5: Audience-specific address | G5: Christ's premortal volunteering is a sentence any disciple can pray; offer what you have, the multiplication is not your job. | H5: FIVE, deliberately small: Caribbean mother and son; Ghana lunches; Cambodia activity kits; Chloe and Eli (both 10) addressing business leaders; the Primary boy raising a congregation's hands. Plus her father's 'now AND later'. | I5: Offer, then listen. Pray 'Here am I, send me,' then stop and listen for thoughts and ideas. | J5: Abraham 3:27; Matt 14:15-21; John 6:5-13; Alma 37:6; 38:9; Ether 4:12; D&C 93:29; 130:18; 1 Cor 2:9; Family Proclamation | K5: 'Holding Hands Around the World' (Hymns for Home and Church) | L5: Oaks 2025; Ezra Taft Benson BYU 1974 | M5: Prophet + one predecessor | N5: n.10 the full Benson passage on turning your life over to God. | O5: None. | P5: 12 Handoff | Q5: X | T5: X | Y5: X | AB5: X | AC5: Durable Promise | AD5: Children as inviters - the transmission running upward from child to adult, three separate times. | AE5: 1, 9, 12 | AF5: D7 | AG5: Three Questions of Life (external confirmation) | AH5: STANDOUT CORRELATION: Identity, Purpose, Destiny stated in order, from the Family Proclamation, to eight-year-olds. Cleanest external confirmation the Three Questions have received.
A6: 5 | B6: Neil L. Andersen | C6: Quorum of the Twelve | D6: Eternal Marriage Is an Eternal Journey | E6: 11:42 | F6: Testimony-narrative | G6: Eternal marriage is a crucible of becoming, not a status achieved at an altar; difficulty is part of the design. | H6: FOUR: kneeling across the altar from Kathy; the Shakespeare napkins kept around the apartment; President Packer's 'It is for Kathy!'; and the fifty-year marriage told through the son - depression, the father on his knees and quietly fasting again, later cancer and neurological illness, 'they did it together through the final day.' | I6: None explicit. | J6: Luke 24:5-6; Matt 16:19; D&C 132:19-20; 131:1-4; Isa 40:28-31; Family Proclamation | K6: Shakespeare, Sonnet 116 | L6: Hinckley 1993; Nelson 1995 'Perfection Pending'; Oaks BYU Feb 2026, 1993, 2007; Faust 1993; Brigham Young; Joseph Fielding Smith; Willoughby 2021 | M6: Predecessors + one apostle | N6: MAJOR. n.14 carries his divorce teaching, stated in the address as reserved for the published version. n.4 Nelson 'Perfection Pending' in full. | O6: n.5 Willoughby, The Millennial Marriage (2021) - sociology of eroding marriage confidence. | P6: 7 Cohesion | V6: X | W6: X | X6: X | AA6: X | AB6: X | AC6: Fixed Center; Durable Promise | AD6: Fifty-year case; the cost borne by the well spouse across two illness eras. | AE6: 1, 7, 8, 12 | AF6: M8 | AG6: RM Climb Wall 7 & Wall 1 | AH6: 'Perfection Pending' is the single most useful item for the RM's central anxiety: the divine attributes will not all be perfected in this life.
A7: 6 | B7: Quentin L. Cook | C7: Quorum of the Twelve | D7: Keys, Covenants, and Easter | E7: 11:32 | F7: Testimony-narrative | G7: Elijah's sealing keys, restored Easter Sunday 1836 in Kirtland, are essential; without them no eternal families. | H7: Temple open-house tours with Elder Holland for rabbis and Jewish leaders from 2009; the twelve oxen and 1 Kings 7:25 bringing tears; Holland overcome in the sealing room; Orson Hyde 175th anniversary in Jerusalem; two former companions and their wives reading the Gospels beside the Garden Tomb. | I7: Re-inhabit the ignorance - ask what a 17-year-old with only a Bible would have asked, then answer from scratch. | J7: D&C 2:1-3; Mal 4:5-6; D&C 110; 128:8-9,17; 138:47-48; JS-H 1:27-54; Luke 9:28-36; 3 Ne 25:5; 1 Kgs 7:23-25 | K7: None. | L7: Joseph Smith; Christofferson 2023; Eyring 2005; Bednar 2011; Nelson 2024; Hunter; Ricks (BYU Studies 1983) | M7: Apostles + academic | N7: n.9 Joseph Smith on why Elijah; n.14 Jews still set a place for Elijah at the seder. | O7: n.5 Ricks, BYU Studies 23:4 (1983) on Kirtland and Passover; n.13 Quran 37:123-26. | P7: 12 Handoff | R7: X | V7: X | AB7: X | AC7: Fixed Center | AD7: n/a | AE7: 2, 12 | AF7: Q6 | AG7: Production Line 2 / The Common Tongue (RICHEST FEED); dead-side vein (deferred) | AH7: Moroni taught AND RETAUGHT through one night - repetition as the method of a reliable handoff. 'You do not need to physically visit Jerusalem' - study delivers the same confirmation.
A8: 7 | B8: Taniela B. Wakolo | C8: Of the Seventy | D8: Come unto Christ - Together | E8: 8:37 | F8: Testimony-narrative | G8: The temple is a symbol of hope, not pressure; the gospel is a bridge to unite families, not a wedge. | H8: FOUR cases: Denny & Alex (NZ, 2 yrs); the Brisbane 7-year-old and his father (declined, still open); Bob & Marlene Hasenyager (the stake president's one question; sealed 4 months before Bob died); and the Fiji wife who waited 8 years and 24 missionaries - revealed to be his own wife Anita. | I8: Road-sign escalation (stop / 'Full stop' / 'Really you gotta stop'); Moses's two questions (Why? By what means?); the withheld disclosure. | J8: Moses 1:27-33,39; 2 Ne 26:33; D&C 49:15-17; D&C 2:3; Jacob 1:7; Omni 1:26; Moroni 10:32; Ex 3:6,15 | K8: None. | L8: Oaks 2025; Gong 2025 | M8: Two living apostles | N8: None of note. | O8: None. | P8: 11 Force (restraint) | S8: X | W8: X | AA8: X | AC8: Fixed Center | AD8: RICHEST NAZARETH YIELD: four complete case cards with inviter, mode, cost, tempo (2 yrs / open / decades / 8 yrs & 24 missionaries) and a LIVE rejection with the invitation intact. | AE8: 3, 7, 11 | AF8: Q5 | AG8: Nazareth Effect case file; RM loving-unbelievers section | AH8: 'The Savior never forces. He invites.' Nelson's Question Hierarchy (Why then How) in one scriptural instance. Patriarchal blessing enters the corpus here.
A9: 8 | B9: Gerrit W. Gong | C9: Quorum of the Twelve | D9: 'Tis Eastertide: No One Walks Alone | E9: 11:09 | F9: Testimony-narrative | G9: The road to Emmaus is a covenant pattern: He walks with us unrecognized; His word makes the heart burn and His ordinance opens the eyes. | H9: As a new BYU freshman on a panel with the new BYU president, who explained his red tie was for his 40th birthday; and Oaks's story of the grandfather's chest of coins and the granddaughter who took only gold pieces. | I9: Second-person immersion ('Imagine we are walking to Emmaus'); etymology as doorway (Emmaus = hot springs = healing); word-threading on abide/abode. | J9: Luke 24; Mark 16:9-14; John 14-15; John 20:11-15; D&C 20:77,79; Moses 6:34; Matt 6:33; 2 Ne 11:5 | K9: 'Abide with Me; Tis Eventide' (165); 'Abide with Me!' (166); 'I Know That My Redeemer Lives' (136) | L9: Bednar 2023; Oaks 2007; Teachings: Joseph Smith | M9: Apostle + predecessor | N9: MAJOR. n.16 carries a full spoken-nowhere promise to the youth. n.18 quotes 'Abide with Me!' at length. | O9: None. | P9: 7 Cohesion | Q9: X | R9: X | W9: X | Z9: X | AC9: Fixed Center; Durable Promise | AD9: Three unrecognized appearances on one Easter day - absence of recognition is not absence. | AE9: 2, 7 | AF9: W6, W8, M6 | AG9: RM Climb Wall 7 (best closing line); succession record | AH9: Solemn assembly historically anchored and the April 2026 sustainings named. Second apostle in the conference to run the word-threading method (with Bednar on 'endure').

Sheet Marker Coverage
A1: Marker coverage - full conference, 34 addresses
A3: Marker | B3: Sat AM | C3: Sat PM | D3: Sun AM | E3: Sun PM | F3: Total | G3: Read
A4: 1 Vig | B4: =COUNTIF(SatAM!Q2:Q10,"X") -> 3 | C4: =COUNTIF(SatPM!Q2:Q11,"X") -> 4 | D4: =COUNTIF(SunAM!Q2:Q10,"X") -> 4 | E4: =COUNTIF(SunPM!Q2:Q9,"X") -> 2 | F4: =SUM(B4:E4) -> 13 | G4: Watchful ascent; no standing still
A5: 2 Mem | B5: =COUNTIF(SatAM!R2:R10,"X") -> 4 | C5: =COUNTIF(SatPM!R2:R11,"X") -> 3 | D5: =COUNTIF(SunAM!R2:R10,"X") -> 4 | E5: =COUNTIF(SunPM!R2:R9,"X") -> 4 | F5: =SUM(B5:E5) -> 15 | G5: The record plus the living voice
A6: 3 Dev | B6: =COUNTIF(SatAM!S2:S10,"X") -> 3 | C6: =COUNTIF(SatPM!S2:S11,"X") -> 5 | D6: =COUNTIF(SunAM!S2:S10,"X") -> 2 | E6: =COUNTIF(SunPM!S2:S9,"X") -> 3 | F6: =SUM(B6:E6) -> 13 | G6: The undivided heart vs. the blend
A7: 4 Equ | B7: =COUNTIF(SatAM!T2:T10,"X") -> 5 | C7: =COUNTIF(SatPM!T2:T11,"X") -> 2 | D7: =COUNTIF(SunAM!T2:T10,"X") -> 3 | E7: =COUNTIF(SunPM!T2:T9,"X") -> 2 | F7: =SUM(B7:E7) -> 12 | G7: Equity, consecration, no status ladder
A8: 5 Tru | B8: =COUNTIF(SatAM!U2:U10,"X") -> 1 | C8: =COUNTIF(SatPM!U2:U11,"X") -> 3 | D8: =COUNTIF(SunAM!U2:U10,"X") -> 3 | E8: =COUNTIF(SunPM!U2:U9,"X") -> 2 | F8: =SUM(B8:E8) -> 9 | G8: Word-to-deed alignment under cost
A9: 6 Wat | B9: =COUNTIF(SatAM!V2:V10,"X") -> 2 | C9: =COUNTIF(SatPM!V2:V11,"X") -> 3 | D9: =COUNTIF(SunAM!V2:V10,"X") -> 1 | E9: =COUNTIF(SunPM!V2:V9,"X") -> 3 | F9: =SUM(B9:E9) -> 9 | G9: Watchmen on the tower; correction welcomed
A10: 7 Coh | B10: =COUNTIF(SatAM!W2:W10,"X") -> 4 | C10: =COUNTIF(SatPM!W2:W11,"X") -> 3 | D10: =COUNTIF(SunAM!W2:W10,"X") -> 3 | E10: =COUNTIF(SunPM!W2:W9,"X") -> 3 | F10: =SUM(B10:E10) -> 13 | G10: Cohesion of the covenant body
A11: 8 Int | B11: =COUNTIF(SatAM!X2:X10,"X") -> 3 | C11: =COUNTIF(SatPM!X2:X11,"X") -> 2 | D11: =COUNTIF(SunAM!X2:X10,"X") -> 1 | E11: =COUNTIF(SunPM!X2:X9,"X") -> 1 | F11: =SUM(B11:E11) -> 7 | G11: Integrity; the kept word
A12: 9 Lea | B12: =COUNTIF(SatAM!Y2:Y10,"X") -> 3 | C12: =COUNTIF(SatPM!Y2:Y11,"X") -> 2 | D12: =COUNTIF(SunAM!Y2:Y10,"X") -> 2 | E12: =COUNTIF(SunPM!Y2:Y9,"X") -> 2 | F12: =SUM(B12:E12) -> 9 | G12: Servant leadership; whom you follow
A13: 10 For | B13: =COUNTIF(SatAM!Z2:Z10,"X") -> 1 | C13: =COUNTIF(SatPM!Z2:Z11,"X") -> 3 | D13: =COUNTIF(SunAM!Z2:Z10,"X") -> 2 | E13: =COUNTIF(SunPM!Z2:Z9,"X") -> 2 | F13: =SUM(B13:E13) -> 8 | G13: Fortification; guardrails set in advance
A14: 11 Frc | B14: =COUNTIF(SatAM!AA2:AA10,"X") -> 4 | C14: =COUNTIF(SatPM!AA2:AA11,"X") -> 2 | D14: =COUNTIF(SunAM!AA2:AA10,"X") -> 6 | E14: =COUNTIF(SunPM!AA2:AA9,"X") -> 4 | F14: =SUM(B14:E14) -> 16 | G14: Strength restrained by mercy
A15: 12 Han | B15: =COUNTIF(SatAM!AB2:AB10,"X") -> 7 | C15: =COUNTIF(SatPM!AB2:AB11,"X") -> 6 | D15: =COUNTIF(SunAM!AB2:AB10,"X") -> 5 | E15: =COUNTIF(SunPM!AB2:AB9,"X") -> 4 | F15: =SUM(B15:E15) -> 22 | G15: Handoff to the rising generation
A17: Addresses | B17: =COUNTA(SatAM!B2:B10) -> 9 | C17: =COUNTA(SatPM!B2:B11) -> 10 | D17: =COUNTA(SunAM!B2:B10) -> 9 | E17: =COUNTA(SunPM!B2:B9) -> 8 | F17: =SUM(B17:E17) -> 36 | G17: Includes 4 procedural items and 1 placeholder (Christofferson, SunPM)
